ftis/__init__.py
ftis/corpus.py
ftis/filters.py
ftis/process.py
ftis/visualisation.py
ftis/analyser/__init__.py
ftis/analyser/audio.py
ftis/analyser/clustering.py
ftis/analyser/descriptor.py
ftis/analyser/dr.py
ftis/analyser/dsp.py
ftis/analyser/meta.py
ftis/analyser/scaling.py
ftis/analyser/slicing.py
ftis/analyser/stats.py
ftis/common/__init__.py
ftis/common/analyser.py
ftis/common/conversion.py
ftis/common/exceptions.py
ftis/common/io.py
ftis/common/proc.py
ftis/common/types.py
ftis/common/utils.py
ftis-1.1.1.dist-info/METADATA
ftis-1.1.1.dist-info/WHEEL
ftis-1.1.1.dist-info/top_level.txt
ftis-1.1.1.dist-info/RECORD
