Metadata-Version: 2.1
Name: ftis
Version: 1.1.1
Summary: The finding things in stuff package.
Home-page: https://github.com/jamesb93/ftis
Author: James Bradbury
Author-email: jamesbradbury93@gmail.com
License: GLPv3+
Platform: UNKNOWN
Requires-Dist: Soundfile
Requires-Dist: hdbscan
Requires-Dist: umap-learn
Requires-Dist: sklearn
Requires-Dist: python-flucoma
Requires-Dist: pydub
Requires-Dist: scipy
Requires-Dist: rich
Requires-Dist: librosa
